DNMR/__init__.py
DNMR/__main__.py
DNMR/code-reference.pdf
DNMR/fileops.py
DNMR/icon.png
DNMR/icon_transparent.png
DNMR/miniwidgets.py
DNMR/tab.py
DNMR/tab_channel_slice.py
DNMR/tab_field_scan.py
DNMR/tab_fourier_transform.py
DNMR/tab_inv_laplace.py
DNMR/tab_peak_amplitude.py
DNMR/tab_phase_adj.py
DNMR/tab_t1_fitting.py
DNMR/test_file.hdf
DNMR/test_save.csv
DNMR/fileops_loaders/__init__.py
DNMR/fileops_loaders/alpha.py
DNMR/fileops_loaders/data_struct.py
DNMR/fileops_loaders/v100.py
dnmr-1.6.4.dist-info/licenses/LICENSE
dnmr-1.6.4.dist-info/METADATA
dnmr-1.6.4.dist-info/WHEEL
dnmr-1.6.4.dist-info/entry_points.txt
dnmr-1.6.4.dist-info/top_level.txt
dnmr-1.6.4.dist-info/RECORD
