Metadata-Version: 2.4
Name: DNMR
Version: 1.6.4
Summary: A package to analyse the data generated by the frappy/NICOS interface, with the TNMR setup at Paul Scherrer Institut, Villigen, Switzerland
Author-email: "Davis V. Garrad" <davis.last@psi.ch>
License-Expression: GPL-3.0-only
Project-URL: Homepage, https://github.com/Davis-Garrad/DNMR
Project-URL: Issues, https://github.com/Davis-Garrad/DNMR/issues
Classifier: Programming Language :: Python :: 3
Classifier: Operating System :: OS Independent
Requires-Python: >=3.9
License-File: LICENSE
Requires-Dist: h5py
Requires-Dist: numpy<=2.3.0
Requires-Dist: matplotlib
Requires-Dist: PyQt6
Requires-Dist: pandas
Requires-Dist: pytnt
Dynamic: license-file
